r00richi/__init__.py
r00richi/core.py
r00richi-0.1.1.dist-info/METADATA
r00richi-0.1.1.dist-info/WHEEL
r00richi-0.1.1.dist-info/RECORD
