Metadata-Version: 2.4
Name: r00richi
Version: 0.1.1
Requires-Python: >=3.10
Requires-Dist: json-repair
Requires-Dist: pyfiglet
Requires-Dist: rich
